understory/solarized.py
understory_fx-0.0.5.dist-info/LICENSE
understory_fx-0.0.5.dist-info/WHEEL
understory_fx-0.0.5.dist-info/METADATA
understory_fx-0.0.5.dist-info/RECORD
